tests/__init__.py
tests/test_collect.py
tests/test_config.py
tests/test_device.py
tests/test_influx.py
tests/test_mqtt.py
tests/test_time.py
tests/test_vuegraf.py
vuegraf/__init__.py
vuegraf/collect.py
vuegraf/config.py
vuegraf/device.py
vuegraf/influx.py
vuegraf/mqtt.py
vuegraf/time.py
vuegraf/vuegraf.py
vuegraf-1.10.0.dist-info/licenses/LICENSE
vuegraf-1.10.0.dist-info/METADATA
vuegraf-1.10.0.dist-info/WHEEL
vuegraf-1.10.0.dist-info/entry_points.txt
vuegraf-1.10.0.dist-info/top_level.txt
vuegraf-1.10.0.dist-info/RECORD
