Metadata-Version: 2.4
Name: vuegraf
Version: 1.10.0
Summary: Populate metrics from your Emporia Vue energy monitoring devices into an InfluxDB
Home-page: https://github.com/jertel/vuegraf
Author: Jason Ertel
License: MIT
Project-URL: Documentation, https://github.com/jertel/vuegraf
Project-URL: Source Code, https://github.com/jertel/vuegraf
Project-URL: Discussion Forum, https://github.com/jertel/vuegraf/discussions
Classifier: Programming Language :: Python :: 3.12
Classifier: Operating System :: OS Independent
Requires-Python: >=3.12
License-File: LICENSE
Requires-Dist: influxdb>=5.3.2
Requires-Dist: influxdb_client>=1.49.0
Requires-Dist: pyemvue>=0.18.9
Requires-Dist: paho-mqtt>=2.1.0
Requires-Dist: argparse>=1.4.0
Dynamic: author
Dynamic: classifier
Dynamic: description
Dynamic: description-content-type
Dynamic: home-page
Dynamic: license
Dynamic: license-file
Dynamic: project-url
Dynamic: requires-dist
Dynamic: requires-python
Dynamic: summary
